python_sdk_rafay_workflow/__init__.py
python_sdk_rafay_workflow/activity_logger.py
python_sdk_rafay_workflow/app_factory.py
python_sdk_rafay_workflow/const.py
python_sdk_rafay_workflow/errors.py
python_sdk_rafay_workflow/logger.py
python_sdk_rafay_workflow/sdk.py
python_sdk_rafay_workflow/state_client.py
rafay_workflow_sdk-0.0.33.dist-info/METADATA
rafay_workflow_sdk-0.0.33.dist-info/WHEEL
rafay_workflow_sdk-0.0.33.dist-info/licenses/LICENSE
rafay_workflow_sdk-0.0.33.dist-info/RECORD
