Metadata-Version: 2.4
Name: rafay_workflow_sdk
Version: 0.0.33
Summary: Rafay workflow handler Python function SDK
Project-URL: Homepage, https://github.com/RafaySystems/function-templates
Project-URL: Issues, https://github.com/RafaySystems/function-templates/issues
Author-email: Bheema Sarat Chandra Kaki <sarat@rafay.co>, Avinash Varma <avinash@rafay.co>, Akash MC <akash@rafay.co>, Nirav Parikh <nirav.parikh@rafay.co>
License-File: LICENSE
Classifier: License :: OSI Approved :: MIT License
Classifier: Operating System :: OS Independent
Classifier: Programming Language :: Python :: 3
Requires-Python: >=3.11
Requires-Dist: fastapi>=0.104.0
Requires-Dist: gunicorn>=23.0.0
Requires-Dist: httpx>=0.28.1
Requires-Dist: requests>=2.31.0
Requires-Dist: uvicorn[standard]>=0.24.0
Provides-Extra: test
Requires-Dist: backoff>=2.0.0; extra == 'test'
Requires-Dist: pytest-httpserver>=1.0.0; extra == 'test'
Requires-Dist: pytest>=7.0.0; extra == 'test'
Requires-Dist: requests>=2.31.0; extra == 'test'
